responsys/__init__.py
responsys/client.py
responsys/exceptions.py
responsys/types.py
responsys/tests/__init__.py
responsys/tests/integration_config.py
responsys/tests/test_client.py
responsys/tests/test_integration.py
responsys/tests/test_types.py
responsys-0.2.2b1.dist-info/DESCRIPTION.rst
responsys-0.2.2b1.dist-info/METADATA
responsys-0.2.2b1.dist-info/metadata.json
responsys-0.2.2b1.dist-info/pbr.json
responsys-0.2.2b1.dist-info/RECORD
responsys-0.2.2b1.dist-info/top_level.txt
responsys-0.2.2b1.dist-info/WHEEL
