Metadata-Version: 2.0
Name: responsys
Version: 0.2.2b1
Summary: Python client library for the Responsys Interact API
Home-page: https://github.com/jslang/responsys
Author: Jared Lang
Author-email: UNKNOWN
License: GPLv2
Keywords: responsys interact client api
Platform: UNKNOWN
Requires-Dist: suds-jurko
